{
  "name": "Visual Studio",
  "actions": [
    {
      "id": "StepOut",
      "description": "Step Out",
      "fullTextDescription": "Step to the first line executed after returning from this method",
      "shortcuts": [
        {
          "firstKeystroke": "shift F11"
        },
        {
          "firstKeystroke": "shift control F8"
        }
      ]
    },
    {
      "id": "Resume",
      "description": "Resume Program",
      "shortcuts": [
        {
          "firstKeystroke": "F5"
        }
      ]
    },
    {
      "id": "QuickEvaluateExpression",
      "description": "Quick Evaluate Expression",
      "shortcuts": [
        {
          "firstKeystroke": "shift F9"
        }
      ]
    },
    {
      "id": "EditorDeleteLine",
      "description": "Delete Line",
      "shortcuts": [
        {
          "firstKeystroke": "shift control L"
        }
      ]
    },
    {
      "id": "ShowErrorDescription",
      "description": "Error Description",
      "fullTextDescription": "Show description of error or warning at caret",
      "shortcuts": [
        {
          "firstKeystroke": "control F1"
        },
        {
          "firstKeystroke": "alt T"
        }
      ]
    },
    {
      "id": "FindUsages",
      "description": "Find Usages",
      "fullTextDescription": "Find usages of the symbol at caret",
      "shortcuts": [
        {
          "firstKeystroke": "shift alt F7"
        }
      ]
    },
    {
      "id": "StepInto",
      "description": "Step Into",
      "fullTextDescription": "Step to the next line executed",
      "shortcuts": [
        {
          "firstKeystroke": "F11"
        },
        {
          "firstKeystroke": "F8"
        }
      ]
    },
    {
      "id": "ForceStepInto",
      "description": "Force Step Into",
      "fullTextDescription": "Step into, ignore stepping filters for libraries, constructors, etc.",
      "shortcuts": [
        {
          "firstKeystroke": "alt F11"
        },
        {
          "firstKeystroke": "alt F8"
        }
      ]
    },
    {
      "id": "Cut",
      "description": "Cut",
      "shortcuts": [
        {
          "firstKeystroke": "control X"
        },
        {
          "firstKeystroke": "shift DELETE"
        }
      ]
    },
    {
      "id": "Compile",
      "description": "Rebuild",
      "fullTextDescription": "Force recompilation for selected module, file or package",
      "shortcuts": [
        {
          "firstKeystroke": "control F7"
        }
      ]
    },
    {
      "id": "ReformatCode",
      "description": "Reformat Code",
      "shortcuts": [
        {
          "firstKeystroke": "alt F8"
        },
        {
          "firstKeystroke": "control alt F"
        }
      ]
    },
    {
      "id": "Generate",
      "description": "Generate...",
      "fullTextDescription": "Generate constructor, getter or setter method, etc.",
      "shortcuts": [
        {
          "firstKeystroke": "control N"
        },
        {
          "firstKeystroke": "alt INSERT"
        }
      ]
    },
    {
      "id": "ShowExecutionPoint",
      "description": "Show Execution Point",
      "fullTextDescription": "Show the current program execution point",
      "shortcuts": [
        {
          "firstKeystroke": "alt MULTIPLY"
        },
        {
          "firstKeystroke": "control L"
        }
      ]
    },
    {
      "id": "Paste",
      "description": "Paste",
      "shortcuts": [
        {
          "firstKeystroke": "control V"
        },
        {
          "firstKeystroke": "shift INSERT"
        }
      ]
    },
    {
      "id": "CommentByBlockComment",
      "description": "Comment with Block Comment",
      "shortcuts": [
        {
          "firstKeystroke": "shift control SLASH"
        },
        {
          "firstKeystroke": "shift control DIVIDE"
        },
        {
          "firstKeystroke": "shift control COLON"
        }
      ]
    },
    {
      "id": "JumpToLastWindow",
      "description": "Jump to Last Tool Window",
      "shortcuts": []
    },
    {
      "id": "StepOver",
      "description": "Step Over",
      "fullTextDescription": "Step to the next line in this file",
      "shortcuts": [
        {
          "firstKeystroke": "F10"
        },
        {
          "firstKeystroke": "shift F8"
        }
      ]
    },
    {
      "id": "GotoTypeDeclaration",
      "description": "Type Declaration",
      "fullTextDescription": "Navigate to the declaration of the symbol\u0027s type at caret",
      "shortcuts": [
        {
          "firstKeystroke": "shift alt F12"
        },
        {
          "firstKeystroke": "shift alt F2"
        }
      ]
    },
    {
      "id": "Copy",
      "description": "Copy",
      "shortcuts": [
        {
          "firstKeystroke": "control C"
        },
        {
          "firstKeystroke": "control INSERT"
        }
      ]
    },
    {
      "id": "GotoClass",
      "description": "Class...",
      "fullTextDescription": "Quickly navigate to a class by name",
      "shortcuts": [
        {
          "firstKeystroke": "control COMMA"
        }
      ]
    },
    {
      "id": "GotoChangedFile",
      "description": "Go To Changed File...",
      "fullTextDescription": "Quickly navigate to changed file by name",
      "shortcuts": [
        {
          "firstKeystroke": "control COMMA"
        }
      ],
      "actionGroup": "Diff \u0026 Merge"
    },
    {
      "id": "ParameterInfo",
      "description": "Parameter Info",
      "fullTextDescription": "Show parameters of the method call at caret",
      "shortcuts": [
        {
          "firstKeystroke": "shift control SPACE"
        }
      ]
    },
    {
      "id": "ExpressionTypeInfo",
      "description": "Type Info",
      "fullTextDescription": "Show type of the selected expression",
      "shortcuts": []
    },
    {
      "id": "RunClass",
      "description": "Run",
      "shortcuts": [
        {
          "firstKeystroke": "control F9"
        }
      ]
    },
    {
      "id": "FindNext",
      "description": "Find Next / Move to Next Occurrence",
      "fullTextDescription": "Repeat the last Find/Replace operation, or moving to next occurrence of selected text",
      "shortcuts": [
        {
          "firstKeystroke": "F3"
        }
      ]
    },
    {
      "id": "Print",
      "description": "Print...",
      "shortcuts": [
        {
          "firstKeystroke": "control P"
        }
      ]
    },
    {
      "id": "ImplementMethods",
      "description": "Implement Methods...",
      "fullTextDescription": "Implement base interface/class methods in the current class",
      "shortcuts": [
        {
          "firstKeystroke": "shift control I"
        }
      ]
    },
    {
      "id": "SmartTypeCompletion",
      "description": "SmartType",
      "fullTextDescription": "Complete code basing on expected type",
      "shortcuts": [
        {
          "firstKeystroke": "shift alt SPACE"
        }
      ]
    },
    {
      "id": "GotoDeclaration",
      "description": "Declaration or Usages",
      "fullTextDescription": "Navigate to the declaration of the symbol at caret or show its usages",
      "shortcuts": [
        {
          "firstKeystroke": "F12"
        },
        {
          "firstKeystroke": "shift F2"
        },
        {
          "firstKeystroke": "control B"
        }
      ]
    },
    {
      "id": "NewElement",
      "description": "New...",
      "fullTextDescription": "Create new class, interface, file or directory",
      "shortcuts": [
        {
          "firstKeystroke": "alt INSERT"
        }
      ]
    },
    {
      "id": "FindPrevious",
      "description": "Find Previous / Move to Previous Occurrence",
      "fullTextDescription": "Repeat the last Find/Replace operation in reverse direction, or moving to previous occurrence of selected text",
      "shortcuts": [
        {
          "firstKeystroke": "shift F3"
        }
      ]
    },
    {
      "id": "FindUsagesInFile",
      "description": "Find Usages in File",
      "fullTextDescription": "Find usages of the symbol at caret in active editor",
      "shortcuts": [
        {
          "firstKeystroke": "shift control F7"
        },
        {
          "firstKeystroke": "shift F12"
        }
      ]
    },
    {
      "id": "CompileDirty",
      "description": "Build Project",
      "fullTextDescription": "Compile all modified and dependent files in the project",
      "shortcuts": [
        {
          "firstKeystroke": "F7"
        }
      ]
    },
    {
      "id": "GotoLine",
      "description": "Line/Column...",
      "fullTextDescription": "Navigate to a line (and/or column) in editor by its number",
      "shortcuts": [
        {
          "firstKeystroke": "control G"
        }
      ]
    },
    {
      "id": "JumpToLastChange",
      "description": "Last Edit Location",
      "fullTextDescription": "Move through the most recent change points",
      "shortcuts": [
        {
          "firstKeystroke": "shift control F2"
        }
      ]
    },
    {
      "id": "EditorCodeBlockEnd",
      "description": "Move Caret to Code Block End",
      "shortcuts": [
        {
          "firstKeystroke": "control CLOSE_BRACKET"
        },
        {
          "firstKeystroke": "control ASTERISK"
        }
      ]
    },
    {
      "id": "OverrideMethods",
      "description": "Override Methods...",
      "fullTextDescription": "Override base class methods in the current class",
      "shortcuts": [
        {
          "firstKeystroke": "shift control O"
        }
      ]
    },
    {
      "id": "ToggleLineBreakpoint",
      "description": "Toggle Line Breakpoint",
      "shortcuts": [
        {
          "firstKeystroke": "F9"
        }
      ]
    },
    {
      "id": "ToggleBookmark",
      "description": "Toggle Bookmark",
      "fullTextDescription": "Toggle bookmark at the current location",
      "shortcuts": [
        {
          "firstKeystroke": "control F2"
        }
      ]
    },
    {
      "id": "Pause",
      "description": "Pause Program",
      "fullTextDescription": "Suspend program execution and enable debugging",
      "shortcuts": [
        {
          "firstKeystroke": "control PAUSE"
        },
        {
          "firstKeystroke": "shift control P"
        }
      ]
    },
    {
      "id": "Stop",
      "description": "Stop",
      "shortcuts": [
        {
          "firstKeystroke": "shift F5"
        }
      ]
    },
    {
      "id": "StopBackgroundProcesses",
      "description": "Stop Background Processes...",
      "shortcuts": [
        {
          "firstKeystroke": "shift control F5"
        }
      ]
    },
    {
      "id": "CommentByLineComment",
      "description": "Comment with Line Comment",
      "fullTextDescription": "Comment/uncomment current line or selected block with line comments",
      "shortcuts": [
        {
          "firstKeystroke": "control SLASH"
        },
        {
          "firstKeystroke": "control DIVIDE"
        },
        {
          "firstKeystroke": "control COLON"
        }
      ]
    },
    {
      "id": "RunToCursor",
      "description": "Run to Cursor",
      "fullTextDescription": "Run to the line where the caret is",
      "shortcuts": [
        {
          "firstKeystroke": "control F10"
        },
        {
          "firstKeystroke": "control F8"
        }
      ]
    },
    {
      "id": "QuickJavaDoc",
      "description": "Quick Documentation",
      "fullTextDescription": "Show a popup window with documentation for the symbol at caret",
      "shortcuts": [
        {
          "firstKeystroke": "control Q"
        }
      ]
    },
    {
      "id": "ShowBookmarks",
      "description": "Show Bookmarks",
      "shortcuts": [
        {
          "firstKeystroke": "alt F2"
        }
      ]
    },
    {
      "id": "ViewBreakpoints",
      "description": "View Breakpoints...",
      "fullTextDescription": "View and manage all breakpoints and watchpoints",
      "shortcuts": [
        {
          "firstKeystroke": "alt F9"
        }
      ]
    },
    {
      "id": "EditBreakpoint",
      "description": "Edit breakpoint",
      "shortcuts": [
        {
          "firstKeystroke": "alt F9"
        }
      ]
    },
    {
      "id": "TypeHierarchy",
      "description": "Type Hierarchy",
      "fullTextDescription": "Browse hierarchy for the selected class",
      "shortcuts": [
        {
          "firstKeystroke": "alt H"
        }
      ]
    },
    {
      "id": "EditorCodeBlockStart",
      "description": "Move Caret to Code Block Start",
      "shortcuts": [
        {
          "firstKeystroke": "control OPEN_BRACKET"
        }
      ]
    },
    {
      "id": "Replace",
      "description": "Replace...",
      "fullTextDescription": "Replace a string in active editor with another string",
      "shortcuts": [
        {
          "firstKeystroke": "control H"
        }
      ]
    },
    {
      "id": "OpenFile",
      "description": "Open...",
      "fullTextDescription": "Open a project or a file in editor",
      "shortcuts": [
        {
          "firstKeystroke": "control O"
        }
      ]
    },
    {
      "id": "Refresh",
      "description": "Refresh",
      "shortcuts": [
        {
          "firstKeystroke": "control alt R"
        }
      ]
    },
    {
      "id": "ForceRefresh",
      "description": "Force Refresh",
      "shortcuts": [
        {
          "firstKeystroke": "control alt shift R"
        }
      ]
    },
    {
      "id": "ExternalJavaDoc",
      "description": "External Documentation",
      "fullTextDescription": "Open browser with documentation for the selected item",
      "shortcuts": [
        {
          "firstKeystroke": "shift F1"
        },
        {
          "firstKeystroke": "control F1"
        }
      ]
    },
    {
      "id": "VcsShowNextChangeMarker",
      "description": "Next Change",
      "shortcuts": [
        {
          "firstKeystroke": "shift control alt DOWN"
        }
      ]
    },
    {
      "id": "VcsShowPrevChangeMarker",
      "description": "Previous Change",
      "shortcuts": [
        {
          "firstKeystroke": "shift control alt UP"
        }
      ]
    },
    {
      "id": "GotoNextElementUnderCaretUsage",
      "description": "Go to next highlighted element usage",
      "shortcuts": [
        {
          "firstKeystroke": "alt shift D"
        }
      ]
    },
    {
      "id": "GotoPrevElementUnderCaretUsage",
      "description": "Go to previous highlighted element usage",
      "shortcuts": [
        {
          "firstKeystroke": "alt shift U"
        }
      ]
    },
    {
      "id": "CopyElement",
      "description": "Copy...",
      "fullTextDescription": "Create a copy of the selected class, file(s) or directory(es)",
      "shortcuts": []
    },
    {
      "id": "Rerun",
      "description": "Rerun",
      "shortcuts": []
    }
  ]
}